openstates/__init__.py
openstates/cli/__init__.py
openstates/cli/committees.py
openstates/cli/convert_us.py
openstates/cli/initdb.py
openstates/cli/makemigrations.py
openstates/cli/people.py
openstates/cli/people_repo_update.py
openstates/cli/relationships.py
openstates/cli/reports.py
openstates/cli/scrape.py
openstates/cli/tests/__init__.py
openstates/cli/tests/test_initdb.py
openstates/cli/tests/test_session_report.py
openstates/cli/tests/test_settings.py
openstates/cli/text_extract.py
openstates/cli/update.py
openstates/cli/update_computed.py
openstates/cli/validate.py
openstates/data/__init__.py
openstates/data/admin/__init__.py
openstates/data/admin/base.py
openstates/data/admin/bill.py
openstates/data/admin/event.py
openstates/data/admin/organization.py
openstates/data/admin/other.py
openstates/data/admin/person.py
openstates/data/admin/reports.py
openstates/data/admin/vote.py
openstates/data/common.py
openstates/data/migrations/0001_initial.py
openstates/data/migrations/0002_auto_20200422_0028.py
openstates/data/migrations/0003_auto_20200422_0031.py
openstates/data/migrations/0004_auto_20200422_0040.py
openstates/data/migrations/0005_auto_20200423_1100.py
openstates/data/migrations/0006_auto_20200423_1124.py
openstates/data/migrations/0007_auto_20200423_1416.py
openstates/data/migrations/0008_person_current_state.py
openstates/data/migrations/0009_auto_20200429_0913.py
openstates/data/migrations/0010_auto_20200721_1604.py
openstates/data/migrations/0011_auto_20200804_1108.py
openstates/data/migrations/0012_person_current_role.py
openstates/data/migrations/0013_remove_person_current_state.py
openstates/data/migrations/0014_remove_person_current_role_division_id.py
openstates/data/migrations/0015_auto_20200811_1009.py
openstates/data/migrations/0016_auto_20200811_1016.py
openstates/data/migrations/0017_remove_person_summary.py
openstates/data/migrations/0018_auto_20200914_1032.py
openstates/data/migrations/0019_remove_billabstract_date.py
openstates-6.24.7.dist-info/METADATA
openstates-6.24.7.dist-info/WHEEL
openstates-6.24.7.dist-info/entry_points.txt
openstates-6.24.7.dist-info/licenses/LICENSE
openstates-6.24.7.dist-info/RECORD
